[
    {
        "no": 1,
        "date": 1,
        "timeperiod": "morning",
        "from": "family",
        "topic": "news",
        "howmedium": "talking"
    },
    {
        "no": 2,
        "date": 1,
        "timeperiod": "morning",
        "from": "friends",
        "topic": "design&art",
        "howmedium": "wechat/weibo"
    },
    {
        "no": 3,
        "date": 1,
        "timeperiod": "afternoon",
        "from": "friends",
        "topic": "personal experience",
        "howmedium": "phone call"
    },
    {
        "no": 4,
        "date": 1,
        "timeperiod": "afternoon",
        "from": "friends",
        "topic": "news",
        "howmedium": "wechat/weibo"
    },
    {
        "no": 5,
        "date": 2,
        "timeperiod": "evening ",
        "from": "friends",
        "topic": "design&art",
        "howmedium": "wechat/weibo"
    },
    {
        "no": 6,
        "date": 2,
        "timeperiod": "evening ",
        "from": "friends",
        "topic": "tech",
        "howmedium": "video/website"
    },
    {
        "no": 7,
        "date": 2,
        "timeperiod": "evening ",
        "from": "class",
        "topic": "tech",
        "howmedium": "video/website"
    },
    {
        "no": 8,
        "date": 2,
        "timeperiod": "afternoon",
        "from": "teammate",
        "topic": "design&art",
        "howmedium": "wechat/weibo"
    },
    {
        "no": 9,
        "date": 2,
        "timeperiod": "afternoon",
        "from": "friends",
        "topic": "entertainment ",
        "howmedium": "video/website"
    },
    {
        "no": 10,
        "date": 2,
        "timeperiod": "afternoon",
        "from": "friends",
        "topic": "entertainment",
        "howmedium": "video/website"
    },
    {
        "no": 11,
        "date": 3,
        "timeperiod": "morning",
        "from": "class",
        "topic": "news",
        "howmedium": "video/website"
    },
    {
        "no": 12,
        "date": 3,
        "timeperiod": "afternoon",
        "from": "class",
        "topic": "design&art",
        "howmedium": "video/website"
    },
    {
        "no": 13,
        "date": 3,
        "timeperiod": "afternoon",
        "from": "class",
        "topic": "design&art",
        "howmedium": "video/website"
    },
    {
        "no": 14,
        "date": 3,
        "timeperiod": "afternoon",
        "from": "friends",
        "topic": "news",
        "howmedium": "wechat/weibo"
    },
    {
        "no": 15,
        "date": 3,
        "timeperiod": "evening ",
        "from": "friends",
        "topic": "news",
        "howmedium": "video/website"
    },
    {
        "no": 16,
        "date": 4,
        "timeperiod": "morning",
        "from": "friends",
        "topic": "personal experience",
        "howmedium": "wechat/weibo"
    },
    {
        "no": 17,
        "date": 4,
        "timeperiod": "afternoon",
        "from": "friends",
        "topic": "personal experience",
        "howmedium": "phone call"
    },
    {
        "no": 18,
        "date": 5,
        "timeperiod": "morning",
        "from": "teammate",
        "topic": "news",
        "howmedium": "meeting"
    },
    {
        "no": 19,
        "date": 5,
        "timeperiod": "morning",
        "from": "teammate",
        "topic": "tech",
        "howmedium": "meeting"
    },
    {
        "no": 20,
        "date": 5,
        "timeperiod": "morning",
        "from": "teammate",
        "topic": "business",
        "howmedium": "meeting"
    },
    {
        "no": 21,
        "date": 5,
        "timeperiod": "afternoon",
        "from": "family",
        "topic": "news",
        "howmedium": "talking"
    },
    {
        "no": 22,
        "date": 5,
        "timeperiod": "evening ",
        "from": "friends",
        "topic": "personal experience",
        "howmedium": "phone call"
    },
    {
        "no": 23,
        "date": 5,
        "timeperiod": "evening ",
        "from": "friends",
        "topic": "entertainment",
        "howmedium": "wechat/weibo"
    },
    {
        "no": 24,
        "date": 6,
        "timeperiod": "morning",
        "from": "friends",
        "topic": "news",
        "howmedium": "wechat/weibo"
    },
    {
        "no": 25,
        "date": 6,
        "timeperiod": "morning",
        "from": "friends",
        "topic": "entertainment",
        "howmedium": "wechat/weibo"
    },
    {
        "no": 26,
        "date": 6,
        "timeperiod": "evening ",
        "from": "teammate",
        "topic": "news",
        "howmedium": "meeting"
    },
    {
        "no": 27,
        "date": 7,
        "timeperiod": "morning",
        "from": "friends",
        "topic": "news",
        "howmedium": "wechat/weibo"
    },
    {
        "no": 28,
        "date": 7,
        "timeperiod": "morning",
        "from": "friends",
        "topic": "news",
        "howmedium": "wechat/weibo"
    },
    {
        "no": 29,
        "date": 7,
        "timeperiod": "afternoon",
        "from": "class",
        "topic": "tech",
        "howmedium": "video/website"
    },
    {
        "no": 30,
        "date": 7,
        "timeperiod": "evening",
        "from": "teammate",
        "topic": "business",
        "howmedium": "wechat/weibo"
    },
    {
        "no": 31,
        "date": 7,
        "timeperiod": "evening",
        "from": "friends",
        "topic": "news",
        "howmedium": "wechat/weibo"
    },
    {
        "no": 32,
        "date": 7,
        "timeperiod": "evening",
        "from": "friends",
        "topic": "design&art",
        "howmedium": "wechat/weibo"
    },
    {
        "no": 33,
        "date": 8,
        "timeperiod": "afternoon",
        "from": "family",
        "topic": "design&art",
        "howmedium": "talking"
    }
]
